itime/__init__.py
itime-0.0.1.dist-info/LICENSE
itime-0.0.1.dist-info/METADATA
itime-0.0.1.dist-info/WHEEL
itime-0.0.1.dist-info/top_level.txt
itime-0.0.1.dist-info/RECORD
