Metadata-Version: 2.1
Name: itime
Version: 0.0.1
Summary: awesome converter for various time formata
Home-page: https://github.com/slxiao/itime
Author: Shelwin Xiao
Author-email: shliangxiao@gmail.com
License: MIT
Platform: UNKNOWN
Classifier: License :: OSI Approved :: MIT License
Classifier: Programming Language :: Python
Classifier: Programming Language :: Python :: 2
Classifier: Programming Language :: Python :: 3
Requires-Dist: pytz
Requires-Dist: calendar
